difflog/__init__.py
difflog/__main__.py
difflog/diff.py
difflog/git_report.py
difflog/module_member.py
difflog-0.0.2.dist-info/licenses/LICENSE
difflog-0.0.2.dist-info/METADATA
difflog-0.0.2.dist-info/WHEEL
difflog-0.0.2.dist-info/entry_points.txt
difflog-0.0.2.dist-info/top_level.txt
difflog-0.0.2.dist-info/zip-safe
difflog-0.0.2.dist-info/RECORD
