Metadata-Version: 2.4
Name: difflog
Version: 0.0.2
Summary: A static analysis tool for diffing public Python APIs.
Author-email: jon-edward <townsend.jonathan.e@gmail.com>
License-Expression: Apache-2.0
Project-URL: Homepage, https://github.com/jon-edward/difflog
Project-URL: Source, https://github.com/jon-edward/difflog
Keywords: python,static analysis,api diffing
Platform: Linux
Platform: Windows
Platform: MacOS
Classifier: Development Status :: 4 - Beta
Classifier: Environment :: Console
Classifier: Natural Language :: English
Classifier: Operating System :: OS Independent
Classifier: Programming Language :: Python
Classifier: Programming Language :: Python :: 3
Classifier: Programming Language :: Python :: 3.10
Classifier: Programming Language :: Python :: 3.11
Classifier: Programming Language :: Python :: 3.12
Classifier: Programming Language :: Python :: 3.13
Classifier: Programming Language :: Python :: Implementation :: CPython
Requires-Python: <4.0,>=3.10
License-File: LICENSE
Requires-Dist: deepdiff>=8.5.0
Provides-Extra: test
Requires-Dist: pytest; extra == "test"
Dynamic: license-file
